piwiPre/__init__.py
piwiPre/__main__.py
piwiPre/pwgVideologo.py
piwiPre/pwpActor.py
piwiPre/pwpArgsIni.py
piwiPre/pwpConfig.py
piwiPre/pwpConfigurator.py
piwiPre/pwpData.py
piwiPre/pwpDir.py
piwiPre/pwpElevate.py
piwiPre/pwpErrors.py
piwiPre/pwpGui.py
piwiPre/pwpImageEmbedder.py
piwiPre/pwpInstaller.py
piwiPre/pwpJpg.py
piwiPre/pwpLicence.py
piwiPre/pwpLogoSmall.py
piwiPre/pwpMain.py
piwiPre/pwpMp4.py
piwiPre/pwpParser.py
piwiPre/pwpPatcher.py
piwiPre/pwpVersion.py
piwiPre-0.23.8.dist-info/LICENCE
piwiPre-0.23.8.dist-info/METADATA
piwiPre-0.23.8.dist-info/WHEEL
piwiPre-0.23.8.dist-info/entry_points.txt
piwiPre-0.23.8.dist-info/top_level.txt
piwiPre-0.23.8.dist-info/RECORD
