Metadata-Version: 2.1
Name: piwiPre
Version: 0.23.8
Summary: pictures & video preparation tool for piwigo
Home-page: https://gitlab.com/fabien.battini/piwipre
Author: Fabien BATTINI
Author-email: fabien.battini@gmail.com
Keywords: piwigo images pictures video
Classifier: Programming Language :: Python :: 3
Classifier: License :: OSI Approved :: European Union Public Licence 1.2 (EUPL 1.2)
Classifier: Operating System :: OS Independent
Classifier: Development Status :: 5 - Production/Stable
Classifier: Intended Audience :: End Users/Desktop
Classifier: Topic :: Office/Business :: Office Suites
Requires-Python: >=3.6
License-File: LICENCE
